ena_upload/__init__.py
ena_upload/_version.py
ena_upload/check_remote.py
ena_upload/ena_upload.py
ena_upload/json_parsing/__init__.py
ena_upload/json_parsing/characteristic.py
ena_upload/json_parsing/ena_experiment.py
ena_upload/json_parsing/ena_run.py
ena_upload/json_parsing/ena_sample.py
ena_upload/json_parsing/ena_std_lib.py
ena_upload/json_parsing/ena_study.py
ena_upload/json_parsing/ena_submission.py
ena_upload/json_parsing/other_material.py
ena_upload/json_parsing/json_schemas/assay_schema.json
ena_upload/json_parsing/json_schemas/comment_schema.json
ena_upload/json_parsing/json_schemas/data_schema.json
ena_upload/json_parsing/json_schemas/factor_schema.json
ena_upload/json_parsing/json_schemas/factor_value_schema.json
ena_upload/json_parsing/json_schemas/investigation_schema.json
ena_upload/json_parsing/json_schemas/material_attribute_schema.json
ena_upload/json_parsing/json_schemas/material_attribute_value_schema.json
ena_upload/json_parsing/json_schemas/material_schema.json
ena_upload/json_parsing/json_schemas/ontology_annotation_schema.json
ena_upload/json_parsing/json_schemas/ontology_source_reference_schema.json
ena_upload/json_parsing/json_schemas/organization_schema.json
ena_upload/json_parsing/json_schemas/person_schema.json
ena_upload/json_parsing/json_schemas/process_parameter_value_schema.json
ena_upload/json_parsing/json_schemas/process_schema.json
ena_upload/json_parsing/json_schemas/protocol_parameter_schema.json
ena_upload/json_parsing/json_schemas/protocol_schema.json
ena_upload/json_parsing/json_schemas/publication_schema.json
ena_upload/json_parsing/json_schemas/sample_schema.json
ena_upload/json_parsing/json_schemas/source_schema.json
ena_upload/json_parsing/json_schemas/study_schema.json
ena_upload/templates/ENA.project.xsd
ena_upload/templates/ENA_template_FASTQFILE.xml
ena_upload/templates/ENA_template_FILE.xml
ena_upload/templates/ENA_template_LIBRARY_SELECTION.xml
ena_upload/templates/ENA_template_LIBRARY_SOURCE.xml
ena_upload_cli-0.9.0.dist-info/licenses/LICENSE
ena_upload_cli-0.9.0.dist-info/METADATA
ena_upload_cli-0.9.0.dist-info/WHEEL
ena_upload_cli-0.9.0.dist-info/entry_points.txt
ena_upload_cli-0.9.0.dist-info/top_level.txt
ena_upload_cli-0.9.0.dist-info/RECORD
