Metadata-Version: 2.4
Name: ena-upload-cli
Version: 0.9.0
Summary: Command Line Interface to upload data to the European Nucleotide Archive
Home-page: https://github.com/usegalaxy-eu/ena-upload-cli
Author: Dilmurat Yusuf
Author-email: bjoern.gruening@gmail.com
License: MIT
Keywords: pip,ena-upload-cli,cli,ENA,upload
Classifier: Operating System :: OS Independent
Requires-Python: >=3.8
License-File: LICENSE
Requires-Dist: genshi==0.7.*
Requires-Dist: lxml==5.3.0
Requires-Dist: pandas<=3.0.0,>=2.0.3
Requires-Dist: pyyaml==6.0.*
Requires-Dist: requests<=3.0.0,>=2.31.0
Requires-Dist: openpyxl<=4.0.0,>=3.1.2
Requires-Dist: jsonschema>=4.19.1
Requires-Dist: pytest==7.4.*
Dynamic: author
Dynamic: author-email
Dynamic: classifier
Dynamic: description
Dynamic: description-content-type
Dynamic: home-page
Dynamic: keywords
Dynamic: license
Dynamic: license-file
Dynamic: requires-dist
Dynamic: requires-python
Dynamic: summary
